ja_law_parser/__init__.py
ja_law_parser/model.py
ja_law_parser/parser.py
ja_law_parser-0.3.0.dist-info/LICENSE
ja_law_parser-0.3.0.dist-info/METADATA
ja_law_parser-0.3.0.dist-info/WHEEL
ja_law_parser-0.3.0.dist-info/RECORD
