Metadata-Version: 2.1
Name: ja-law-parser
Version: 0.3.0
Summary: A Japanese law parser
Home-page: https://github.com/takuyaa/ja-law-parser
License: MIT
Author: Takuya Asano
Author-email: takuya.a@gmail.com
Requires-Python: >=3.9
Classifier: License :: OSI Approved :: MIT License
Classifier: Programming Language :: Python :: 3
Classifier: Programming Language :: Python :: 3.9
Classifier: Programming Language :: Python :: 3.10
Classifier: Programming Language :: Python :: 3.11
Classifier: Programming Language :: Python :: 3.12
Requires-Dist: pydantic (>=2.4.2,<3.0.0)
Requires-Dist: pydantic-xml[lxml] (>=2.3.0,<3.0.0)
Project-URL: Repository, https://github.com/takuyaa/ja-law-parser
